roundmantissa/__init__.py
roundmantissa/jax.py
roundmantissa/numpy.py
roundmantissa-0.2.1.dist-info/LICENSE
roundmantissa-0.2.1.dist-info/METADATA
roundmantissa-0.2.1.dist-info/WHEEL
roundmantissa-0.2.1.dist-info/top_level.txt
roundmantissa-0.2.1.dist-info/RECORD
