Metadata-Version: 2.1
Name: roundmantissa
Version: 0.2.1
Summary: Round mantissa of a float number
Home-page: https://github.com/mariogeiger/roundmantissa
License: MIT
Platform: UNKNOWN
Requires-Python: >=3.7
